{
  "courses": [
    {
      "id": 8,
      "title": "Architecting Applications for the Real World",
      "slug": "architecting-applications-dotnet",
      "authorId": 1,
      "category": "Software Architecture"
    },
    {
      "id": 9,
      "title": "Becoming an Outlier: Reprogramming the Developer Mind",
      "slug": "career-reboot-for-developer-mind",
      "authorId": 1,
      "category": "Career"
    },
    {
      "id": 10,
      "title": "Web Component Fundamentals",
      "slug": "web-components-shadow-dom",
      "authorId": 1,
      "category": "HTML5"
    },
    {
      "id": 11,
      "slug": "sdafsdf",
      "title": "sdafsdf",
      "authorId": 1,
      "category": "sadf",
      "createdAt": 1618807894089
    }
  ],
  "authors": [
    {
      "id": 1,
      "name": "Cory House"
    },
    {
      "id": 2,
      "name": "Scott Allen"
    },
    {
      "id": 3,
      "name": "Dan Wahlin"
    }
  ]
}